karabiner_config_helpers/__init__.py
karabiner_config_helpers/app_layouts.py
karabiner_config_helpers/keyboard_base.py
karabiner_config_helpers/keyboard_de.py
karabiner_config_helpers/keyboard_us.py
karabiner_config_helpers/rules.py
karabiner_config_helpers/script_utils.py
karabiner_config_helpers/type_utils.py
karabiner_config_helpers-0.0.2.data/scripts/karabiner-rules
karabiner_config_helpers-0.0.2.data/scripts/karabiner-type
karabiner_config_helpers-0.0.2.dist-info/METADATA
karabiner_config_helpers-0.0.2.dist-info/WHEEL
karabiner_config_helpers-0.0.2.dist-info/top_level.txt
karabiner_config_helpers-0.0.2.dist-info/RECORD
