Metadata-Version: 2.1
Name: karabiner-config-helpers
Version: 0.0.2
Summary: Useful functions and tools for custom karabiner element rules.
Home-page: https://gitlab.com/six-two/karabiner-config
Author: six-two
Author-email: pip@six-two.dev
License: MIT License
Classifier: License :: OSI Approved :: MIT License
Classifier: Operating System :: POSIX :: Linux
Classifier: Programming Language :: Python :: 3
Classifier: Programming Language :: Python :: 3.9
Classifier: Programming Language :: Python :: 3.10
Classifier: Programming Language :: Python :: 3.11
Requires-Python: >=3.9
